pygredients/__init__.py
pygredients/linkedlist/__init__.py
pygredients/linkedlist/linkedlist.py
pygredients/linkedlist/test_linkedlist.py
pygredients/node/__init__.py
pygredients/node/node.py
pygredients/node/test_node.py
pygredients/observer/__init__.py
pygredients/observer/observer.py
pygredients/observer/test_observer.py
pygredients/queue/__init__.py
pygredients/queue/adapter_queue.py
pygredients/queue/queue.py
pygredients/queue/test_queue.py
pygredients/stack/__init__.py
pygredients/stack/stack.py
pygredients/stack/test_stack.py
pygredients-0.1.3.dist-info/LICENSE.txt
pygredients-0.1.3.dist-info/METADATA
pygredients-0.1.3.dist-info/WHEEL
pygredients-0.1.3.dist-info/top_level.txt
pygredients-0.1.3.dist-info/RECORD
